{
  "schemaVersion": 1,
  "id": 8,
  "sentence": {
    "en": "is the same voice that will applaud you one day.",
    "ar": "هو نفس الصوت الذي سيصفّق لك يومًا ما.",
    "context": "تشجيع على تحويل التحدي الداخلي إلى مصدر تحفيز."
  },
  "lesson": {
    "wordMeanings": [
      {
        "term": "is",
        "description": "فعل be في الحاضر مع المفرد."
      },
      {
        "term": "the",
        "description": "أداة تعريف تشير إلى شيء معروف أو محدد."
      },
      {
        "term": "same",
        "description": "صفة تعني نفسه أو نفس الشيء."
      },
      {
        "term": "voice",
        "description": "اسم يعني الذي."
      },
      {
        "term": "that",
        "description": "تشير إلى أمر أو خبر سبق ذكره."
      },
      {
        "term": "will",
        "description": "أداة مستقبل تدل على ما سيحدث لاحقًا."
      },
      {
        "term": "applaud",
        "description": "فعل يعني سيصفق."
      },
      {
        "term": "you",
        "description": "الضمير الذي يعود على الشخص المخاطَب."
      },
      {
        "term": "one",
        "description": "كلمة تدل على العدد واحد أو على شيء واحد."
      },
      {
        "term": "day",
        "description": "اسم يعني يوم."
      }
    ],
    "tense": "المستقبل البسيط",
    "tenseEn": "Future Simple",
    "tenseReason": "استُعمل المستقبل البسيط لأن الجملة تتحدث عن شيء سيحدث لاحقًا أو عن قرار أو توقع يخص المستقبل.",
    "examples": [
      {
        "id": 1,
        "en": "Soon, is the same voice that will applaud you one day.",
        "ar": "قريبًا، هو نفس الصوت الذي سيصفّق لك يومًا ما.",
        "context": "تؤكد قرب الحدث في المستقبل."
      },
      {
        "id": 2,
        "en": "Tomorrow, is the same voice that will applaud you one day.",
        "ar": "غدًا، هو نفس الصوت الذي سيصفّق لك يومًا ما.",
        "context": "تربط الجملة بوقت مستقبلي محدد."
      },
      {
        "id": 3,
        "en": "is the same voice that will applaud you one day after lunch.",
        "ar": "هو نفس الصوت الذي سيصفّق لك يومًا ما بعد الغداء.",
        "context": "تضيف توقيتًا مستقبليًا واضحًا."
      },
      {
        "id": 4,
        "en": "is the same voice that will applaud you one day if everything goes well.",
        "ar": "هو نفس الصوت الذي سيصفّق لك يومًا ما إذا سارت الأمور جيدًا.",
        "context": "تجعل الحدث معتمدًا على شرط مستقبلي."
      },
      {
        "id": 5,
        "en": "is the same voice that will applaud you one day later today.",
        "ar": "هو نفس الصوت الذي سيصفّق لك يومًا ما لاحقًا اليوم.",
        "context": "تربط الجملة بمستقبل قريب جدًا."
      },
      {
        "id": 6,
        "en": "I think is the same voice that will applaud you one day.",
        "ar": "أعتقد أن هو نفس الصوت الذي سيصفّق لك يومًا ما.",
        "context": "تضيف معنى التوقع أو الاعتقاد."
      },
      {
        "id": 7,
        "en": "is the same voice that will applaud you one day, so get ready.",
        "ar": "هو نفس الصوت الذي سيصفّق لك يومًا ما، لذا استعد.",
        "context": "تضيف نتيجة أو استعدادًا لحدث مستقبلي."
      },
      {
        "id": 8,
        "en": "Next week, is the same voice that will applaud you one day.",
        "ar": "الأسبوع القادم، هو نفس الصوت الذي سيصفّق لك يومًا ما.",
        "context": "تنقل الجملة إلى وقت مستقبلي أبعد قليلًا."
      },
      {
        "id": 9,
        "en": "is the same voice that will applaud you one day when the time is right.",
        "ar": "هو نفس الصوت الذي سيصفّق لك يومًا ما عندما يحين الوقت المناسب.",
        "context": "تربط الحدث المستقبلي بوقت مناسب غير محدد."
      },
      {
        "id": 10,
        "en": "Before long, is the same voice that will applaud you one day.",
        "ar": "بعد وقت قصير، هو نفس الصوت الذي سيصفّق لك يومًا ما.",
        "context": "تضيف ظرفًا مستقبليًا عامًا."
      }
    ]
  }
}
