{
  "schemaVersion": 1,
  "id": 9,
  "sentence": {
    "en": "Or “What is going on?”",
    "ar": "أو: \"ما الذي يحدث؟\"",
    "context": "مثال آخر شائع في المحادثات اليومية."
  },
  "lesson": {
    "wordMeanings": [
      {
        "term": "Or",
        "description": "حرف عطف يفيد الاختيار بين شيئين."
      },
      {
        "term": "What",
        "description": "أداة سؤال عن الشيء أو المعنى أو الاختيار."
      },
      {
        "term": "is",
        "description": "فعل be في الحاضر مع المفرد."
      },
      {
        "term": "going",
        "description": "هنا لا تعني يذهب حرفيًا، بل تُستعمل للسؤال عن سير الأمور وتطورها."
      },
      {
        "term": "on",
        "description": "حرف جر يعني على أو في يوم محدد حسب السياق."
      }
    ],
    "tense": "المضارع المستمر",
    "tenseEn": "Present Continuous",
    "tenseReason": "استُعمل المضارع المستمر لأن الجملة تصف شيئًا يحدث الآن أو في فترة قريبة من الآن، أو خطة قريبة واضحة من السياق.",
    "examples": [
      {
        "id": 1,
        "en": "Right now, Or “What is going on?”.",
        "ar": "الآن، أو: \"ما الذي يحدث؟\".",
        "context": "تؤكد أن الفعل يحدث في هذه اللحظة."
      },
      {
        "id": 2,
        "en": "At the moment, Or “What is going on?”.",
        "ar": "في هذه اللحظة، أو: \"ما الذي يحدث؟\".",
        "context": "تؤكد استمرار الحدث الآن."
      },
      {
        "id": 3,
        "en": "Today, Or “What is going on?”.",
        "ar": "اليوم، أو: \"ما الذي يحدث؟\".",
        "context": "تربط الحدث بزمن قريب ومحدد."
      },
      {
        "id": 4,
        "en": "This week, Or “What is going on?”.",
        "ar": "هذا الأسبوع، أو: \"ما الذي يحدث؟\".",
        "context": "توسع الجملة إلى فترة زمنية قريبة."
      },
      {
        "id": 5,
        "en": "Or “What is going on?” because it is important.",
        "ar": "أو: \"ما الذي يحدث؟\" لأنه مهم.",
        "context": "تضيف سببًا للاستمرار في الفعل."
      },
      {
        "id": 6,
        "en": "Or “What is going on?”, so please wait.",
        "ar": "أو: \"ما الذي يحدث؟\"، لذلك انتظر من فضلك.",
        "context": "تضيف نتيجة مباشرة على استمرار الحدث."
      },
      {
        "id": 7,
        "en": "Currently, Or “What is going on?”.",
        "ar": "حاليًا، أو: \"ما الذي يحدث؟\".",
        "context": "تستخدم ظرفًا مناسبًا للحاضر المستمر."
      },
      {
        "id": 8,
        "en": "Or “What is going on?” during this period.",
        "ar": "أو: \"ما الذي يحدث؟\" خلال هذه الفترة.",
        "context": "تربط الفعل بفترة مستمرة لا بلحظة واحدة فقط."
      },
      {
        "id": 9,
        "en": "Or “What is going on?”, and cannot stop now.",
        "ar": "أو: \"ما الذي يحدث؟\"، ولا يمكن التوقف الآن.",
        "context": "تضيف فكرة الاستمرار وعدم التوقف."
      },
      {
        "id": 10,
        "en": "Or “What is going on?” while everyone is watching.",
        "ar": "أو: \"ما الذي يحدث؟\" بينما الجميع يشاهد.",
        "context": "تضيف ظرفًا زمنيًا متزامنًا مع الحدث."
      }
    ]
  }
}
