{
  "schemaVersion": 1,
  "id": 1186,
  "sentence": {
    "en": "I prefer salty or savory foods more than sweet.",
    "ar": "أفضل الأطعمة المالحة أو المتبلة أكثر من الحلوة.",
    "context": "تُستخدم للتعبير عن تفضيل النكهات المالحة أو التي تحتوي على التوابل أو المرق على الحلوة."
  },
  "lesson": {
    "parts": [
      {
        "sentence": "I prefer salty or savory foods more than sweet",
        "ar": "أفضل الأطعمة المالحة أو الغنية بالنكهة أكثر من الحلوة",
        "context": "تصف تفضيلًا في نكهات الطعام.",
        "grammar": {
          "tense": "المضارع البسيط",
          "tenseEn": "Present Simple",
          "reason": "استُخدم المضارع البسيط للتعبير عن تفضيل عام."
        },
        "wordMeanings": [
          {
            "term": "I",
            "description": "ضمير يشير إلى المتكلم"
          },
          {
            "term": "prefer",
            "description": "أفضل"
          },
          {
            "term": "salty",
            "description": "مالح"
          },
          {
            "term": "or",
            "description": "أو"
          },
          {
            "term": "savory",
            "description": "غير حلو وغني بالنكهة"
          },
          {
            "term": "foods",
            "description": "أطعمة"
          },
          {
            "term": "more",
            "description": "أكثر"
          },
          {
            "term": "than",
            "description": "من أو مقارنة بـ"
          },
          {
            "term": "sweet",
            "description": "حلو"
          }
        ]
      }
    ],
    "examples": [
      {
        "id": 1,
        "en": "I prefer salty snacks.",
        "ar": "أفضل الوجبات الخفيفة المالحة.",
        "context": "تُستخدم لتفضيل نكهة."
      },
      {
        "id": 2,
        "en": "She likes savory food more than dessert.",
        "ar": "هي تحب الطعام المالح أكثر من الحلوى.",
        "context": "تُقال عن تفضيل الطعام."
      },
      {
        "id": 3,
        "en": "I do not like very sweet food.",
        "ar": "لا أحب الطعام الحلو جدًا.",
        "context": "تُستخدم لتوضيح الذوق."
      },
      {
        "id": 4,
        "en": "Do you prefer sweet or salty food?",
        "ar": "هل تفضل الطعام الحلو أم المالح؟",
        "context": "تُستخدم للسؤال عن تفضيل."
      },
      {
        "id": 5,
        "en": "I like savory breakfasts.",
        "ar": "أحب وجبات الفطور المالحة.",
        "context": "تُستخدم عن وجبة معينة."
      },
      {
        "id": 6,
        "en": "He prefers chips to candy.",
        "ar": "هو يفضل رقائق البطاطس على الحلوى.",
        "context": "تُستخدم للمقارنة."
      },
      {
        "id": 7,
        "en": "This dish is salty.",
        "ar": "هذا الطبق مالح.",
        "context": "تُستخدم لوصف طبق."
      },
      {
        "id": 8,
        "en": "Sweet food makes me thirsty.",
        "ar": "الطعام الحلو يجعلني عطشانًا.",
        "context": "تُقال عن أثر الطعام."
      },
      {
        "id": 9,
        "en": "I prefer soup to cake.",
        "ar": "أفضل الحساء على الكعك.",
        "context": "تُستخدم لمقارنة طعامين."
      },
      {
        "id": 10,
        "en": "Savory food tastes better to me.",
        "ar": "الطعام المالح ألذ بالنسبة لي.",
        "context": "تُستخدم للتعبير عن الذوق الشخصي."
      }
    ]
  }
}
