{
  "schemaVersion": 1,
  "id": 13,
  "sentence": {
    "en": "He is coming soon.",
    "ar": "هو قادم قريبًا.",
    "context": "ركز على حركة الشخص نحوك."
  },
  "lesson": {
    "wordMeanings": [
      {
        "term": "He",
        "description": "الضمير الذي يعود على شخص مفرد مذكر."
      },
      {
        "term": "is",
        "description": "فعل be يُستعمل هنا مع coming لتكوين المضارع المستمر."
      },
      {
        "term": "coming",
        "description": "فعل مع ing يدل على المجيء الجاري أو المتوقع قريبًا."
      },
      {
        "term": "soon",
        "description": "قريبًا."
      }
    ],
    "tense": "المضارع المستمر",
    "tenseEn": "Present Continuous",
    "tenseReason": "استُعمل المضارع المستمر لأن المتكلم يتحدث عن حركة جارية أو عن ترتيب/وصول قريب مرتبط بالحاضر.",
    "examples": [
      {
        "id": 1,
        "en": "He is coming now.",
        "ar": "هو قادم الآن.",
        "context": "تصف حركة جارية في هذه اللحظة."
      },
      {
        "id": 2,
        "en": "He is coming to the office soon.",
        "ar": "هو قادم إلى المكتب قريبًا.",
        "context": "تخبر عن وصول قريب ومخطط."
      },
      {
        "id": 3,
        "en": "He is coming with me.",
        "ar": "هو قادم معي.",
        "context": "توضح أنه سيتحرك معك."
      },
      {
        "id": 4,
        "en": "He is coming after lunch.",
        "ar": "هو قادم بعد الغداء.",
        "context": "تحدد وقت الوصول القريب."
      },
      {
        "id": 5,
        "en": "He is coming from the station.",
        "ar": "هو قادم من المحطة.",
        "context": "تذكر مكان انطلاقه أو مجيئه."
      },
      {
        "id": 6,
        "en": "He is coming, so wait here.",
        "ar": "هو قادم، لذا انتظر هنا.",
        "context": "تربط المعلومة بتصرف مطلوب."
      },
      {
        "id": 7,
        "en": "He is coming later today.",
        "ar": "هو قادم لاحقًا اليوم.",
        "context": "تتحدث عن قدوم داخل نفس اليوم."
      },
      {
        "id": 8,
        "en": "He is coming to help us.",
        "ar": "هو قادم ليساعدنا.",
        "context": "تذكر سبب المجيء."
      },
      {
        "id": 9,
        "en": "He is coming with the files.",
        "ar": "هو قادم ومعه الملفات.",
        "context": "تضيف معلومة عن ما سيحضره معه."
      },
      {
        "id": 10,
        "en": "He is coming soon, but traffic is heavy.",
        "ar": "هو قادم قريبًا، لكن المرور مزدحم.",
        "context": "تجمع بين التوقع القريب وعامل قد يبطئ."
      }
    ]
  }
}
