{
  "schemaVersion": 1,
  "id": 2009,
  "sentence": {
    "en": "The train leaves at midnight.",
    "ar": "القطار يغادر عند منتصف الليل.",
    "context": "الإشارة إلى موعد انطلاق وسيلة نقل في بداية يوم جديد."
  },
  "lesson": {
    "wordMeanings": [
      {
        "term": "The",
        "description": "أداة تعريف تشير إلى شيء معروف أو محدد."
      },
      {
        "term": "train",
        "description": "اسم يعني قطار."
      },
      {
        "term": "leaves",
        "description": "فعل يعني منتصف."
      },
      {
        "term": "at",
        "description": "حرف جر يعني عند أو في وقت/مكان محدد."
      },
      {
        "term": "midnight",
        "description": "اسم يعني الليل."
      }
    ],
    "tense": "المضارع البسيط",
    "tenseEn": "Present Simple",
    "tenseReason": "استُعمل المضارع البسيط لأن الجملة تعبّر عن حقيقة أو عادة أو حالة عامة أو معنى حاضر في الوقت الحالي.",
    "examples": [
      {
        "id": 1,
        "en": "People often say, \"The train leaves at midnight\" in situations like this.",
        "ar": "يقول الناس كثيرًا: \"القطار يغادر عند منتصف الليل\" في مواقف كهذه.",
        "context": "تستخدم الجملة بوصفها تركيبًا شائعًا في موقف مشابه."
      },
      {
        "id": 2,
        "en": "You can say, \"The train leaves at midnight\" when this happens.",
        "ar": "يمكنك أن تقول: \"القطار يغادر عند منتصف الليل\" عندما يحدث هذا.",
        "context": "توضح أن الجملة مناسبة في موقف متكرر."
      },
      {
        "id": 3,
        "en": "I heard someone say, \"The train leaves at midnight\".",
        "ar": "سمعت شخصًا يقول: \"القطار يغادر عند منتصف الليل\".",
        "context": "تجعل الجملة جزءًا من كلام سمعته من شخص آخر."
      },
      {
        "id": 4,
        "en": "The teacher used the sentence, \"The train leaves at midnight\" in class.",
        "ar": "استخدم المعلم الجملة: \"القطار يغادر عند منتصف الليل\" في الصف.",
        "context": "تستخدم الجملة مثالًا تعليميًا في الصف."
      },
      {
        "id": 5,
        "en": "Many learners remember the sentence, \"The train leaves at midnight\" first.",
        "ar": "يتذكر كثير من المتعلمين الجملة: \"القطار يغادر عند منتصف الليل\" أولًا.",
        "context": "تقدم الجملة بوصفها جملة تعليمية أساسية."
      },
      {
        "id": 6,
        "en": "She said, \"The train leaves at midnight\" in a calm way.",
        "ar": "قالت: \"القطار يغادر عند منتصف الليل\" بطريقة هادئة.",
        "context": "تجعل الجملة جزءًا من كلام مباشر في موقف عادي."
      },
      {
        "id": 7,
        "en": "He repeated, \"The train leaves at midnight\" more than once.",
        "ar": "ردد: \"القطار يغادر عند منتصف الليل\" أكثر من مرة.",
        "context": "تضيف معنى التكرار لنفس الجملة."
      },
      {
        "id": 8,
        "en": "At the right moment, someone might say, \"The train leaves at midnight\".",
        "ar": "في اللحظة المناسبة، قد يقول شخص ما: \"القطار يغادر عند منتصف الليل\".",
        "context": "توضح أن الجملة مرتبطة بتوقيت مناسب في السياق."
      },
      {
        "id": 9,
        "en": "I wrote down the sentence, \"The train leaves at midnight\" so I would remember it.",
        "ar": "كتبت الجملة: \"القطار يغادر عند منتصف الليل\" حتى أتذكرها.",
        "context": "تعطي مثالًا على حفظ الجملة أو مراجعتها."
      },
      {
        "id": 10,
        "en": "It is useful to know when to say, \"The train leaves at midnight\".",
        "ar": "من المفيد أن تعرف متى تقول: \"القطار يغادر عند منتصف الليل\".",
        "context": "تركز على معرفة الوقت المناسب لاستخدام الجملة."
      }
    ]
  }
}
