{
  "schemaVersion": 1,
  "id": 404,
  "sentence": {
    "en": "We are late.",
    "ar": "نحن متأخرون.",
    "context": "الإشارة إلى التأخر عن الموعد المحدد."
  },
  "lesson": {
    "parts": [
      {
        "sentence": "We are late.",
        "ar": "نحن متأخرون.",
        "context": "تستخدم هذه الجملة في سياق: الإشارة إلى التأخر عن الموعد المحدد.",
        "grammar": {
          "tense": "المضارع البسيط",
          "tenseEn": "Present Simple",
          "reason": "يستخدم المضارع البسيط لعرض معلومة حالية أو حقيقة مباشرة في وقت الكلام."
        },
        "wordMeanings": [
          {
            "term": "We",
            "description": "ضمير يشير إلى المتكلم ومعه آخرون"
          },
          {
            "term": "are",
            "description": "صيغة تستخدم مع المخاطب أو الجمع في الحاضر"
          },
          {
            "term": "late",
            "description": "يعني متأخرين عن الموعد"
          }
        ]
      }
    ],
    "examples": [
      {
        "id": 1,
        "en": "I am late.",
        "ar": "أنا متأخر.",
        "context": "يقال عند التأخر عن موعد."
      },
      {
        "id": 2,
        "en": "She is late.",
        "ar": "هي متأخرة.",
        "context": "يناسب وصف تأخر شخص واحد."
      },
      {
        "id": 3,
        "en": "They are late.",
        "ar": "هم متأخرون.",
        "context": "يستخدم عند تأخر مجموعة."
      },
      {
        "id": 4,
        "en": "We are early.",
        "ar": "نحن مبكرون.",
        "context": "يقال عند الوصول قبل الموعد."
      },
      {
        "id": 5,
        "en": "We are on time.",
        "ar": "نحن في الوقت المحدد.",
        "context": "يناسب الوصول في الموعد."
      },
      {
        "id": 6,
        "en": "The bus is late.",
        "ar": "الحافلة متأخرة.",
        "context": "يستخدم عند تأخر وسيلة نقل."
      },
      {
        "id": 7,
        "en": "The meeting is late.",
        "ar": "الاجتماع متأخر.",
        "context": "يقال عند تأخر بداية اجتماع."
      },
      {
        "id": 8,
        "en": "We are ten minutes late.",
        "ar": "نحن متأخرون عشر دقائق.",
        "context": "يناسب تحديد مقدار التأخير."
      },
      {
        "id": 9,
        "en": "He is late for work.",
        "ar": "هو متأخر عن العمل.",
        "context": "يستخدم في سياق العمل."
      },
      {
        "id": 10,
        "en": "I am late for class.",
        "ar": "أنا متأخر عن الدرس.",
        "context": "يقال في سياق الدراسة."
      }
    ]
  }
}
