{
  "schemaVersion": 1,
  "id": 810,
  "sentence": {
    "en": "Yes.",
    "ar": "نعم.",
    "context": "رد بالإيجاب على سؤال ما."
  },
  "lesson": {
    "wordMeanings": [
      {
        "term": "Yes",
        "description": "جواب مباشر يفيد الموافقة أو التأكيد أو الإقرار بصحة شيء."
      }
    ],
    "tense": null,
    "tenseReason": "استُعملت لأنها تؤدي وظيفة الرد السريع بالإيجاب، لا وظيفة وصف حدث في زمن معيّن.",
    "examples": [
      {
        "id": 1,
        "en": "Yes, I am ready.",
        "ar": "نعم، أنا جاهز.",
        "context": "تؤكد أنك مستعد."
      },
      {
        "id": 2,
        "en": "Yes, that is correct.",
        "ar": "نعم، هذا صحيح.",
        "context": "توافق على معلومة أو إجابة."
      },
      {
        "id": 3,
        "en": "Yes, I know her.",
        "ar": "نعم، أنا أعرفها.",
        "context": "تؤكد معرفتك بشخص."
      },
      {
        "id": 4,
        "en": "Yes, we can start now.",
        "ar": "نعم، يمكننا أن نبدأ الآن.",
        "context": "توافق على بدء شيء."
      },
      {
        "id": 5,
        "en": "Yes, I understand.",
        "ar": "نعم، أنا أفهم.",
        "context": "تؤكد أنك فهمت الكلام."
      },
      {
        "id": 6,
        "en": "Yes, I sent the email.",
        "ar": "نعم، لقد أرسلت البريد.",
        "context": "تؤكد أنك أنهيت أمرًا مطلوبًا."
      },
      {
        "id": 7,
        "en": "Yes, he is here.",
        "ar": "نعم، هو هنا.",
        "context": "تؤكد وجود شخص في المكان."
      },
      {
        "id": 8,
        "en": "Yes, I would like that.",
        "ar": "نعم، أود ذلك.",
        "context": "توافق على اقتراح أو عرض."
      },
      {
        "id": 9,
        "en": "Yes, this is my bag.",
        "ar": "نعم، هذه حقيبتي.",
        "context": "تؤكد ملكية شيء."
      },
      {
        "id": 10,
        "en": "Yes, everything is fine.",
        "ar": "نعم، كل شيء بخير.",
        "context": "تطمئن الشخص أن الوضع جيد."
      }
    ]
  }
}
