{
  "schemaVersion": 1,
  "id": 858,
  "sentence": {
    "en": "It is raining.",
    "ar": "إنها تمطر.",
    "context": "لوصف حالة الطقس الحالية."
  },
  "lesson": {
    "parts": [
      {
        "sentence": "It is raining.",
        "ar": "إنها تمطر.",
        "context": "جملة تصف المطر وهو يحدث الآن.",
        "grammar": {
          "tense": "المضارع المستمر",
          "tenseEn": "Present Continuous",
          "reason": "يستخدم المضارع المستمر لوصف حدث يحدث في هذه اللحظة، وit يستخدم للحديث عن الطقس."
        },
        "wordMeanings": [
          {
            "term": "It",
            "description": "تستخدم هنا للحديث عن الطقس"
          },
          {
            "term": "is",
            "description": "صيغة مساعدة مع it في المضارع المستمر"
          },
          {
            "term": "raining",
            "description": "تمطر أو ينزل المطر"
          }
        ]
      }
    ],
    "examples": [
      {
        "id": 1,
        "en": "It is snowing.",
        "ar": "إنها تثلج.",
        "context": "لوصف تساقط الثلج الآن."
      },
      {
        "id": 2,
        "en": "It is raining outside.",
        "ar": "إنها تمطر في الخارج.",
        "context": "لإخبار شخص بحالة الطقس خارجا."
      },
      {
        "id": 3,
        "en": "Is it raining?",
        "ar": "هل تمطر؟",
        "context": "للسؤال عن المطر الآن."
      },
      {
        "id": 4,
        "en": "It is raining hard.",
        "ar": "إنها تمطر بغزارة.",
        "context": "لوصف شدة المطر."
      },
      {
        "id": 5,
        "en": "It is still raining.",
        "ar": "ما زالت تمطر.",
        "context": "للتعبير عن استمرار المطر."
      },
      {
        "id": 6,
        "en": "The phone is ringing.",
        "ar": "الهاتف يرن.",
        "context": "لوصف حدث يحدث الآن."
      },
      {
        "id": 7,
        "en": "The baby is sleeping.",
        "ar": "الطفل نائم.",
        "context": "لوصف حالة حالية."
      },
      {
        "id": 8,
        "en": "It is getting cold.",
        "ar": "الجو يزداد برودة.",
        "context": "لوصف تغير الطقس الآن."
      },
      {
        "id": 9,
        "en": "It is raining today.",
        "ar": "إنها تمطر اليوم.",
        "context": "لوصف طقس اليوم."
      },
      {
        "id": 10,
        "en": "Water is leaking.",
        "ar": "الماء يتسرب.",
        "context": "لوصف مشكلة تحدث الآن."
      }
    ]
  }
}
