{
  "schemaVersion": 1,
  "id": 1,
  "sentence": {
    "en": "Your results are excellent!",
    "ar": "نتائجك ممتازة!",
    "context": "مدح أداء الطالب."
  },
  "lesson": {
    "wordMeanings": [
      {
        "term": "Your",
        "description": "صفة ملكية تعني خاصتك أو خاصتكم."
      },
      {
        "term": "results",
        "description": "اسم يعني نتائجك."
      },
      {
        "term": "are",
        "description": "فعل be مع you."
      },
      {
        "term": "excellent",
        "description": "كلمة تقييم قوية جدًا تعني ممتاز."
      }
    ],
    "tense": "المضارع البسيط",
    "tenseEn": "Present Simple",
    "tenseReason": "استُعمل المضارع البسيط لأن الجملة تعبّر عن حقيقة أو عادة أو حالة عامة أو معنى حاضر في الوقت الحالي.",
    "examples": [
      {
        "id": 1,
        "en": "In general, Your results are excellent!.",
        "ar": "بشكل عام، نتائجك ممتازة!.",
        "context": "تضيف عبارة عامة تحافظ على نفس المعنى الأساسي."
      },
      {
        "id": 2,
        "en": "Usually, Your results are excellent!.",
        "ar": "عادةً، نتائجك ممتازة!.",
        "context": "تضيف ظرفًا يدل على التكرار أو العادة."
      },
      {
        "id": 3,
        "en": "Sometimes, Your results are excellent!.",
        "ar": "أحيانًا، نتائجك ممتازة!.",
        "context": "تضع الجملة في سياق أقل تكرارًا."
      },
      {
        "id": 4,
        "en": "For now, Your results are excellent!.",
        "ar": "في الوقت الحالي، نتائجك ممتازة!.",
        "context": "تربط الجملة بالوضع الحالي."
      },
      {
        "id": 5,
        "en": "Your results are excellent!, so that helps a lot.",
        "ar": "نتائجك ممتازة!، وهذا يساعد كثيرًا.",
        "context": "تضيف نتيجة بسيطة على نفس المعنى."
      },
      {
        "id": 6,
        "en": "Your results are excellent! in daily life.",
        "ar": "نتائجك ممتازة! في الحياة اليومية.",
        "context": "تربط الجملة بمواقف الحياة اليومية."
      },
      {
        "id": 7,
        "en": "Your results are excellent! when it is necessary.",
        "ar": "نتائجك ممتازة! عندما يكون ذلك ضروريًا.",
        "context": "تربط الجملة بشرط أو حاجة معينة."
      },
      {
        "id": 8,
        "en": "In this situation, Your results are excellent!.",
        "ar": "في هذا الموقف، نتائجك ممتازة!.",
        "context": "تجعل الجملة جزءًا من موقف واضح."
      },
      {
        "id": 9,
        "en": "Your results are excellent!, and everyone notices that.",
        "ar": "نتائجك ممتازة!، والجميع يلاحظ ذلك.",
        "context": "تضيف ملاحظة أو نتيجة بعد الجملة."
      },
      {
        "id": 10,
        "en": "Your results are excellent! most of the time.",
        "ar": "نتائجك ممتازة! معظم الوقت.",
        "context": "تضيف عبارة تكرار شائعة."
      }
    ]
  }
}
